crystmatch/__init__.py
crystmatch/analysis.py
crystmatch/enumeration.py
crystmatch/utilities.py
crystmatch-2.1.2.dist-info/licenses/COPYING
crystmatch-2.1.2.dist-info/licenses/THIRD_PARTY_LICENSES
crystmatch-2.1.2.dist-info/METADATA
crystmatch-2.1.2.dist-info/WHEEL
crystmatch-2.1.2.dist-info/entry_points.txt
crystmatch-2.1.2.dist-info/top_level.txt
crystmatch-2.1.2.dist-info/RECORD
