Metadata-Version: 2.4
Name: crystmatch
Version: 2.1.2
Summary: Enumerating and analyzing crystal-structure matches for solid-solid phase transitions.
Home-page: https://fangcheng-wang.github.io/crystmatch/
Author: Fang-Cheng Wang
Author-email: wfc@pku.edu.cn
Classifier: Programming Language :: Python :: 3
Classifier: Operating System :: OS Independent
Requires-Python: >=3.9
License-File: COPYING
License-File: THIRD_PARTY_LICENSES
Requires-Dist: numpy
Requires-Dist: scipy
Requires-Dist: spglib
Requires-Dist: numba
Requires-Dist: matplotlib
Requires-Dist: tqdm
Dynamic: author
Dynamic: author-email
Dynamic: classifier
Dynamic: description
Dynamic: description-content-type
Dynamic: home-page
Dynamic: license-file
Dynamic: requires-dist
Dynamic: requires-python
Dynamic: summary
